README.rst
setup.py
ibex/__init__.py
ibex/_adapter.py
ibex/_base.py
ibex/_function_transformer.py
ibex/_utils.py
ibex/_xy_estimator.py
ibex.egg-info/PKG-INFO
ibex.egg-info/SOURCES.txt
ibex.egg-info/dependency_links.txt
ibex.egg-info/not-zip-safe
ibex.egg-info/top_level.txt
ibex/sklearn/__init__.py
ibex/sklearn/_classification_coef_intercept.py
ibex/sklearn/_cluster.py
ibex/sklearn/_cross_val_predict.py
ibex/sklearn/_decomposition.py
ibex/sklearn/_feature_importances.py
ibex/sklearn/_feature_selection.py
ibex/sklearn/_pipeline.py
ibex/sklearn/_predict_star.py
ibex/sklearn/_preprocessing.py
ibex/sklearn/_regression_coef_intercept.py
ibex/tensorflow/__init__.py
ibex/tensorflow/contrib/__init__.py
ibex/tensorflow/contrib/keras/__init__.py
ibex/tensorflow/contrib/keras/wrappers/__init__.py
ibex/tensorflow/contrib/keras/wrappers/scikit_learn/__init__.py
ibex/xgboost/__init__.py