Metadata-Version: 1.1
Name: ibex
Version: 0.1.3
Summary: Pandas Adapters For Scikit-Learn
Home-page: https://github.com/atavory/ibex
Author: Ami Tavory, Shahar Azulay, Tali Raveh-Sadka
Author-email: atavory@gmail.com
License: bsd
Platform: UNKNOWN
Classifier: Development Status :: 4 - Beta
Classifier: Environment :: Console
Classifier: Intended Audience :: Science/Research
Classifier: License :: OSI Approved :: BSD License
Classifier: Operating System :: OS Independent
Classifier: Programming Language :: Python
Classifier: Programming Language :: Python :: 2
Classifier: Programming Language :: Python :: 3
Classifier: Topic :: Scientific/Engineering
Classifier: Topic :: Scientific/Engineering :: Information Analysis
